wiki_mcp_server.py
iflow_mcp_behinduall_wiki_js_mcp-1.0.0.dist-info/METADATA
iflow_mcp_behinduall_wiki_js_mcp-1.0.0.dist-info/WHEEL
iflow_mcp_behinduall_wiki_js_mcp-1.0.0.dist-info/entry_points.txt
iflow_mcp_behinduall_wiki_js_mcp-1.0.0.dist-info/licenses/LICENSE
iflow_mcp_behinduall_wiki_js_mcp-1.0.0.dist-info/RECORD
