Metadata-Version: 2.4
Name: iflow-mcp_behinduall_wiki-js-mcp
Version: 1.0.0
Summary: Model Context Protocol (MCP) server for Wiki.js integration with hierarchical documentation support
License: MIT
License-File: LICENSE
Author: Sahil Pethe
Author-email: workpethesahil@proton.me
Requires-Python: >=3.12,<4.0
Classifier: License :: OSI Approved :: MIT License
Classifier: Programming Language :: Python :: 3
Classifier: Programming Language :: Python :: 3.12
Classifier: Programming Language :: Python :: 3.13
Classifier: Programming Language :: Python :: 3.14
Requires-Dist: aiosqlite (>=0.19.0,<0.20.0)
Requires-Dist: beautifulsoup4 (>=4.12,<5.0)
Requires-Dist: fastmcp (>=0.1.0,<0.2.0)
Requires-Dist: httpx (>=0.27.0,<0.28.0)
Requires-Dist: markdown (>=3.5,<4.0)
Requires-Dist: pydantic (>=2.0,<3.0)
Requires-Dist: pydantic-settings (>=2.0,<3.0)
Requires-Dist: python-dotenv (>=1.0.0,<2.0.0)
Requires-Dist: python-slugify (>=8.0,<9.0)
Requires-Dist: sqlalchemy (>=2.0,<3.0)
Requires-Dist: tenacity (>=8.0,<9.0)
